{
  "legislative_session": "2026",
  "identifier": "SB00127",
  "title": "AN ACT INCREASING FUNDING FOR HIGHER EDUCATION.",
  "from_organization": "~{\"classification\": \"upper\"}",
  "classification": [
    "bill"
  ],
  "subject": [
    "Board of Regents for Higher Education",
    "Community colleges",
    "Connecticut State Colleges and Universities",
    "State funds",
    "University of Connecticut"
  ],
  "abstracts": [],
  "other_titles": [],
  "other_identifiers": [
    {
      "identifier": "ocd-bill-ct-2026-sb127"
    }
  ],
  "actions": [
    {
      "description": "REF. TO JOINT COMM. ON Appropriations",
      "date": "2026-02-11",
      "organization_id": "~{\"classification\": \"upper\"}",
      "classification": [
        "referral-committee"
      ],
      "related_entities": [],
      "_processing": {
        "log_file_created": "2026-07-13T06:02:13Z"
      }
    }
  ],
  "sponsorships": [
    {
      "name": "Mae Flexer",
      "classification": "primary",
      "entity_type": "person",
      "primary": true,
      "person_id": "~{\"name\": \"Mae Flexer\"}",
      "organization_id": null
    },
    {
      "name": "Gregory Haddad",
      "classification": "primary",
      "entity_type": "person",
      "primary": true,
      "person_id": "~{\"name\": \"Gregory Haddad\"}",
      "organization_id": null
    },
    {
      "name": "Gary A. Turco",
      "classification": "primary",
      "entity_type": "person",
      "primary": true,
      "person_id": "~{\"name\": \"Gary A. Turco\"}",
      "organization_id": null
    }
  ],
  "related_bills": [],
  "versions": [
    {
      "note": "Proposed Bill",
      "links": [
        {
          "url": "https://www.cga.ct.gov/2026/TOB/S/PDF/2026SB-00127-R00-SB.PDF",
          "media_type": "application/pdf"
        }
      ],
      "date": "",
      "classification": ""
    }
  ],
  "documents": [],
  "citations": [],
  "sources": [
    {
      "url": "ftp://ftp.cga.ct.gov/pub/data/bill_info.csv",
      "note": ""
    },
    {
      "url": "https://www.cga.ct.gov/asp/cgabillstatus/cgabillstatus.asp?selBillType=Bill&bill_num=SB127&which_year=2026",
      "note": ""
    }
  ],
  "extras": {},
  "jurisdiction": {
    "id": "ocd-jurisdiction/country:us/state:ct/government",
    "name": "Connecticut",
    "classification": "state",
    "division_id": "ocd-division/country:us/state:ct"
  },
  "_processing": {
    "logs_latest_update": "2026-07-13T06:02:13Z",
    "text_extraction_latest_update": "2026-07-13T10:45:24.115228Z"
  }
}