{
  "legislative_session": "2026",
  "identifier": "SB00418",
  "title": "AN ACT CONCERNING STREAMLINING CERTAIN DEPARTMENT OF ENERGY AND ENVIRONMENTAL PROTECTION PERMITTING PROCESSES.",
  "from_organization": "~{\"classification\": \"upper\"}",
  "classification": [
    "bill"
  ],
  "subject": [
    "Energy and Environmental Protection, Department of",
    "Environmental permits",
    "Reports"
  ],
  "abstracts": [],
  "other_titles": [],
  "other_identifiers": [
    {
      "identifier": "ocd-bill-ct-2026-sb418"
    }
  ],
  "actions": [
    {
      "description": "REF. TO JOINT COMM. ON Commerce",
      "date": "2026-03-05",
      "organization_id": "~{\"classification\": \"upper\"}",
      "classification": [
        "referral-committee"
      ],
      "related_entities": [],
      "_processing": {
        "log_file_created": "2026-07-13T06:02:14Z"
      }
    },
    {
      "description": "PUBLIC HEARING 0310",
      "date": "2026-03-06",
      "organization_id": "~{\"classification\": \"upper\"}",
      "classification": [],
      "related_entities": [],
      "_processing": {
        "log_file_created": "2026-07-13T06:02:14Z"
      }
    }
  ],
  "sponsorships": [],
  "related_bills": [],
  "versions": [
    {
      "note": "Raised Bill",
      "links": [
        {
          "url": "https://www.cga.ct.gov/2026/TOB/S/PDF/2026SB-00418-R00-SB.PDF",
          "media_type": "application/pdf"
        }
      ],
      "date": "",
      "classification": ""
    }
  ],
  "documents": [],
  "citations": [],
  "sources": [
    {
      "url": "ftp://ftp.cga.ct.gov/pub/data/bill_info.csv",
      "note": ""
    },
    {
      "url": "https://www.cga.ct.gov/asp/cgabillstatus/cgabillstatus.asp?selBillType=Bill&bill_num=SB418&which_year=2026",
      "note": ""
    }
  ],
  "extras": {},
  "jurisdiction": {
    "id": "ocd-jurisdiction/country:us/state:ct/government",
    "name": "Connecticut",
    "classification": "state",
    "division_id": "ocd-division/country:us/state:ct"
  },
  "_processing": {
    "logs_latest_update": "2026-07-13T06:02:14Z",
    "text_extraction_latest_update": "2026-07-13T12:27:06.773575Z"
  }
}